{"upload_date": "20170516", "vcodec": "avc1.4d400c", "extractor": "youtube", "series": null, "chapters": null, "height": 144, "like_count": 47, "duration": 900, "fulltitle": "\u5510\u67cf\u6a4b\uff1a\u516d\u56db\u3001\u90ed\u6587\u8cb4\u8207\u53cd\u8150 \uff08\u4e8c\uff09", "id": "4yuLdrz30m8", "album": null, "view_count": 6140, "playlist": "Uploads from \u5510\u67cf\u6865", "start_time": null, "title": "\u5510\u67cf\u6a4b\uff1a\u516d\u56db\u3001\u90ed\u6587\u8cb4\u8207\u53cd\u8150 \uff08\u4e8c\uff09", "_filename": "20170516_NA_4yuLdrz30m8.mp4", "creator": null, "is_live": null, "playlist_index": 176, "dislike_count": 6, "playlist_id": "UUeBfK3zzgqDQLhBovmguOuQ", "abr": 128, "tags": [], "uploader_url": "http://www.youtube.com/user/tanglung4", "subtitles": {}, "fps": 30, "stretched_ratio": null, "season_number": null, "annotations": null, "webpage_url_basename": "4yuLdrz30m8", "acodec": "mp4a.40.2", "display_id": "4yuLdrz30m8", "automatic_captions": {}, "description": "", "format": "160 - 256x144 (144p)+140 - audio only (DASH audio)", "track": null, "playlist_uploader": "\u5510\u67cf\u6865", "average_rating": null, "uploader": "\u5510\u67cf\u6865", "format_id": "160+140", "episode_number": null, "uploader_id": "tanglung4", "categories": ["News & Politics"], "playlist_title": "Uploads from \u5510\u67cf\u6865", "thumbnails": [{"url": "https://i.ytimg.com/vi/4yuLdrz30m8/maxresdefault.jpg", "id": "0"}], "license": null, "artist": null, "extractor_key": "Youtube", "release_date": null, "alt_title": null, "channel_id": "UCeBfK3zzgqDQLhBovmguOuQ", "thumbnail": "https://i.ytimg.com/vi/4yuLdrz30m8/maxresdefault.jpg", "vbr": null, "ext": "mp4", "release_year": null, "end_time": null, "webpage_url": "https://www.youtube.com/watch?v=4yuLdrz30m8", "formats": [{"http_headers": {"Accept-Charset": "ISO-8859-1,utf-8;q=0.7,*;q=0.7", "Accept-Language": "en-us,en;q=0.5", "Accept-Encoding": "gzip, deflate", "Accept": "text/html,application/xhtml+xml,application/xml;q=0.9,*/*;q=0.8", "User-Agent": "Mozilla/5.0 (X11; Linux x86_64; rv:59.0) Gecko/20100101 Firefox/59.0"}, "format_note": "DASH audio", "protocol": "https", "format": "249 - audio only (DASH audio)", "url": "https://r4---sn-a5msen7s.googlevideo.com/videoplayback?id=o-ALIJ9sEEPf5QikT_nLBjAyt4-Tmd2IiQkPg8-AmO_ZWj&itag=249&source=youtube&requiressl=yes&mm=31%2C26&mn=sn-a5msen7s%2Csn-o097znlk&ms=au%2Conr&mv=m&pl=21&ei=XAvTXNSxB82FkwatuLegDQ&initcwndbps=538750&mime=audio%2Fwebm&gir=yes&clen=4887818&dur=900.041&lmt=1544309384288189&mt=1557334713&fvip=2&keepalive=yes&c=WEB&txp=1301222&ip=155.94.169.201&ipbits=0&expire=1557356476&sparams=ip%2Cipbits%2Cexpire%2Cid%2Citag%2Csource%2Crequiressl%2Cmm%2Cmn%2Cms%2Cmv%2Cpl%2Cei%2Cinitcwndbps%2Cmime%2Cgir%2Cclen%2Cdur%2Clmt&signature=48670C6C7B661F036F2E7EA898E027E318FBC5E9.1E06E8138FE493D500397B2F845CCC95FD5EE0BC&key=yt8&ratebypass=yes", "vcodec": "none", "tbr": 65.8, "abr": 50, "player_url": "/yts/jsbin/player_ias-vflmRtaf6/en_US/base.js", "downloader_options": {"http_chunk_size": 10485760}, "ext": "webm", "filesize": 4887818, "format_id": "249", "quality": -1, "acodec": "opus"}, {"http_headers": {"Accept-Charset": "ISO-8859-1,utf-8;q=0.7,*;q=0.7", "Accept-Language": "en-us,en;q=0.5", "Accept-Encoding": "gzip, deflate", "Accept": "text/html,application/xhtml+xml,application/xml;q=0.9,*/*;q=0.8", "User-Agent": "Mozilla/5.0 (X11; Linux x86_64; rv:59.0) Gecko/20100101 Firefox/59.0"}, "format_note": "DASH audio", "protocol": "https", "format": "171 - audio only (DASH audio)", "url": "https://r4---sn-a5msen7s.googlevideo.com/videoplayback?id=o-ALIJ9sEEPf5QikT_nLBjAyt4-Tmd2IiQkPg8-AmO_ZWj&itag=171&source=youtube&requiressl=yes&mm=31%2C26&mn=sn-a5msen7s%2Csn-o097znlk&ms=au%2Conr&mv=m&pl=21&ei=XAvTXNSxB82FkwatuLegDQ&initcwndbps=538750&mime=audio%2Fwebm&gir=yes&clen=8732411&dur=900.032&lmt=1544309389488122&mt=1557334713&fvip=2&keepalive=yes&c=WEB&txp=1301222&ip=155.94.169.201&ipbits=0&expire=1557356476&sparams=ip%2Cipbits%2Cexpire%2Cid%2Citag%2Csource%2Crequiressl%2Cmm%2Cmn%2Cms%2Cmv%2Cpl%2Cei%2Cinitcwndbps%2Cmime%2Cgir%2Cclen%2Cdur%2Clmt&signature=28EF9B0B46608ADACEA523A78D42891B4E68F5B8.BD0E1C9552CD8DD398ECA500B8B2A43379097897&key=yt8&ratebypass=yes", "vcodec": "none", "tbr": 81.585, "abr": 128, "player_url": "/yts/jsbin/player_ias-vflmRtaf6/en_US/base.js", "downloader_options": {"http_chunk_size": 10485760}, "ext": "webm", "filesize": 8732411, "format_id": "171", "quality": -1, "acodec": "vorbis"}, {"http_headers": {"Accept-Charset": "ISO-8859-1,utf-8;q=0.7,*;q=0.7", "Accept-Language": "en-us,en;q=0.5", "Accept-Encoding": "gzip, deflate", "Accept": "text/html,application/xhtml+xml,application/xml;q=0.9,*/*;q=0.8", "User-Agent": "Mozilla/5.0 (X11; Linux x86_64; rv:59.0) Gecko/20100101 Firefox/59.0"}, "format_note": "DASH audio", "protocol": "https", "format": "250 - audio only (DASH audio)", "url": "https://r4---sn-a5msen7s.googlevideo.com/videoplayback?id=o-ALIJ9sEEPf5QikT_nLBjAyt4-Tmd2IiQkPg8-AmO_ZWj&itag=250&source=youtube&requiressl=yes&mm=31%2C26&mn=sn-a5msen7s%2Csn-o097znlk&ms=au%2Conr&mv=m&pl=21&ei=XAvTXNSxB82FkwatuLegDQ&initcwndbps=538750&mime=audio%2Fwebm&gir=yes&clen=6548395&dur=900.041&lmt=1544309388983866&mt=1557334713&fvip=2&keepalive=yes&c=WEB&txp=1301222&ip=155.94.169.201&ipbits=0&expire=1557356476&sparams=ip%2Cipbits%2Cexpire%2Cid%2Citag%2Csource%2Crequiressl%2Cmm%2Cmn%2Cms%2Cmv%2Cpl%2Cei%2Cinitcwndbps%2Cmime%2Cgir%2Cclen%2Cdur%2Clmt&signature=9DBA9101F522A51F880018F0B88235B55E5BFF19.19CDC12C335145A52C663072F94296FB8141EA57&key=yt8&ratebypass=yes", "vcodec": "none", "tbr": 86.6, "abr": 70, "player_url": "/yts/jsbin/player_ias-vflmRtaf6/en_US/base.js", "downloader_options": {"http_chunk_size": 10485760}, "ext": "webm", "filesize": 6548395, "format_id": "250", "quality": -1, "acodec": "opus"}, {"http_headers": {"Accept-Charset": "ISO-8859-1,utf-8;q=0.7,*;q=0.7", "Accept-Language": "en-us,en;q=0.5", "Accept-Encoding": "gzip, deflate", "Accept": "text/html,application/xhtml+xml,application/xml;q=0.9,*/*;q=0.8", "User-Agent": "Mozilla/5.0 (X11; Linux x86_64; rv:59.0) Gecko/20100101 Firefox/59.0"}, "tbr": 98.949, "container": "m4a_dash", "format": "140 - audio only (DASH audio)", "url": "https://r4---sn-a5msen7s.googlevideo.com/videoplayback?id=o-ALIJ9sEEPf5QikT_nLBjAyt4-Tmd2IiQkPg8-AmO_ZWj&itag=140&source=youtube&requiressl=yes&mm=31%2C26&mn=sn-a5msen7s%2Csn-o097znlk&ms=au%2Conr&mv=m&pl=21&ei=XAvTXNSxB82FkwatuLegDQ&initcwndbps=538750&mime=audio%2Fmp4&gir=yes&clen=10967294&dur=900.075&lmt=1544305269132474&mt=1557334713&fvip=2&keepalive=yes&c=WEB&txp=1311222&ip=155.94.169.201&ipbits=0&expire=1557356476&sparams=ip%2Cipbits%2Cexpire%2Cid%2Citag%2Csource%2Crequiressl%2Cmm%2Cmn%2Cms%2Cmv%2Cpl%2Cei%2Cinitcwndbps%2Cmime%2Cgir%2Cclen%2Cdur%2Clmt&signature=6832FD4C45AC366C109D00076392C797E938DF91.1C620741CBF79D69FDF3A5FB210BB3E16C3CEF49&key=yt8&ratebypass=yes", "vcodec": "none", "format_note": "DASH audio", "abr": 128, "player_url": "/yts/jsbin/player_ias-vflmRtaf6/en_US/base.js", "downloader_options": {"http_chunk_size": 10485760}, "ext": "m4a", "filesize": 10967294, "protocol": "https", "format_id": "140", "quality": -1, "acodec": "mp4a.40.2"}, {"http_headers": {"Accept-Charset": "ISO-8859-1,utf-8;q=0.7,*;q=0.7", "Accept-Language": "en-us,en;q=0.5", "Accept-Encoding": "gzip, deflate", "Accept": "text/html,application/xhtml+xml,application/xml;q=0.9,*/*;q=0.8", "User-Agent": "Mozilla/5.0 (X11; Linux x86_64; rv:59.0) Gecko/20100101 Firefox/59.0"}, "format_note": "DASH audio", "protocol": "https", "format": "251 - audio only (DASH audio)", "url": "https://r4---sn-a5msen7s.googlevideo.com/videoplayback?id=o-ALIJ9sEEPf5QikT_nLBjAyt4-Tmd2IiQkPg8-AmO_ZWj&itag=251&source=youtube&requiressl=yes&mm=31%2C26&mn=sn-a5msen7s%2Csn-o097znlk&ms=au%2Conr&mv=m&pl=21&ei=XAvTXNSxB82FkwatuLegDQ&initcwndbps=538750&mime=audio%2Fwebm&gir=yes&clen=9948464&dur=900.041&lmt=1544309386479371&mt=1557334713&fvip=2&keepalive=yes&c=WEB&txp=1301222&ip=155.94.169.201&ipbits=0&expire=1557356476&sparams=ip%2Cipbits%2Cexpire%2Cid%2Citag%2Csource%2Crequiressl%2Cmm%2Cmn%2Cms%2Cmv%2Cpl%2Cei%2Cinitcwndbps%2Cmime%2Cgir%2Cclen%2Cdur%2Clmt&signature=51878964DCFDD85447BFD451A259456924FCA53C.A6CCB18EFC4D0C3DB384B12A77B9E980DC002D65&key=yt8&ratebypass=yes", "vcodec": "none", "tbr": 134.4, "abr": 160, "player_url": "/yts/jsbin/player_ias-vflmRtaf6/en_US/base.js", "downloader_options": {"http_chunk_size": 10485760}, "ext": "webm", "filesize": 9948464, "format_id": "251", "quality": -1, "acodec": "opus"}, {"format_note": "144p", "protocol": "https", "format": "160 - 256x144 (144p)", "tbr": 40.285, "height": 144, "downloader_options": {"http_chunk_size": 10485760}, "format_id": "160", "quality": -1, "http_headers": {"Accept-Charset": "ISO-8859-1,utf-8;q=0.7,*;q=0.7", "Accept-Language": "en-us,en;q=0.5", "Accept-Encoding": "gzip, deflate", "Accept": "text/html,application/xhtml+xml,application/xml;q=0.9,*/*;q=0.8", "User-Agent": "Mozilla/5.0 (X11; Linux x86_64; rv:59.0) Gecko/20100101 Firefox/59.0"}, "url": "https://r4---sn-a5msen7s.googlevideo.com/videoplayback?id=o-ALIJ9sEEPf5QikT_nLBjAyt4-Tmd2IiQkPg8-AmO_ZWj&aitags=133%2C134%2C135%2C136%2C160%2C242%2C243%2C244%2C247%2C278%2C298%2C302&itag=160&source=youtube&requiressl=yes&mm=31%2C26&mn=sn-a5msen7s%2Csn-o097znlk&ms=au%2Conr&mv=m&pl=21&ei=XAvTXNSxB82FkwatuLegDQ&initcwndbps=538750&mime=video%2Fmp4&gir=yes&clen=3140165&dur=899.999&lmt=1544305262182848&mt=1557334713&fvip=2&keepalive=yes&c=WEB&txp=1311222&ip=155.94.169.201&ipbits=0&expire=1557356476&sparams=ip%2Cipbits%2Cexpire%2Cid%2Caitags%2Csource%2Crequiressl%2Cmm%2Cmn%2Cms%2Cmv%2Cpl%2Cei%2Cinitcwndbps%2Cmime%2Cgir%2Cclen%2Cdur%2Clmt&signature=C970476A85984ED4852CECAA798D5E6A5442CBC0.37A3760941F698E477BD584F916B6AA10226BF59&key=yt8&ratebypass=yes", "vcodec": "avc1.4d400c", "player_url": "/yts/jsbin/player_ias-vflmRtaf6/en_US/base.js", "width": 256, "ext": "mp4", "filesize": 3140165, "fps": 30, "acodec": "none"}, {"format_note": "240p", "protocol": "https", "format": "133 - 426x240 (240p)", "tbr": 84.09, "height": 240, "downloader_options": {"http_chunk_size": 10485760}, "format_id": "133", "quality": -1, "http_headers": {"Accept-Charset": "ISO-8859-1,utf-8;q=0.7,*;q=0.7", "Accept-Language": "en-us,en;q=0.5", "Accept-Encoding": "gzip, deflate", "Accept": "text/html,application/xhtml+xml,application/xml;q=0.9,*/*;q=0.8", "User-Agent": "Mozilla/5.0 (X11; Linux x86_64; rv:59.0) Gecko/20100101 Firefox/59.0"}, "url": "https://r4---sn-a5msen7s.googlevideo.com/videoplayback?id=o-ALIJ9sEEPf5QikT_nLBjAyt4-Tmd2IiQkPg8-AmO_ZWj&aitags=133%2C134%2C135%2C136%2C160%2C242%2C243%2C244%2C247%2C278%2C298%2C302&itag=133&source=youtube&requiressl=yes&mm=31%2C26&mn=sn-a5msen7s%2Csn-o097znlk&ms=au%2Conr&mv=m&pl=21&ei=XAvTXNSxB82FkwatuLegDQ&initcwndbps=538750&mime=video%2Fmp4&gir=yes&clen=6563822&dur=899.999&lmt=1544305262377877&mt=1557334713&fvip=2&keepalive=yes&c=WEB&txp=1311222&ip=155.94.169.201&ipbits=0&expire=1557356476&sparams=ip%2Cipbits%2Cexpire%2Cid%2Caitags%2Csource%2Crequiressl%2Cmm%2Cmn%2Cms%2Cmv%2Cpl%2Cei%2Cinitcwndbps%2Cmime%2Cgir%2Cclen%2Cdur%2Clmt&signature=EF45DE65C19BFDB65BC8240DF720532200F0999F.19A950B6F21C174EAA10516266EAAE4231551C5B&key=yt8&ratebypass=yes", "vcodec": "avc1.4d4015", "player_url": "/yts/jsbin/player_ias-vflmRtaf6/en_US/base.js", "width": 426, "ext": "mp4", "filesize": 6563822, "fps": 30, "acodec": "none"}, {"http_headers": {"Accept-Charset": "ISO-8859-1,utf-8;q=0.7,*;q=0.7", "Accept-Language": "en-us,en;q=0.5", "Accept-Encoding": "gzip, deflate", "Accept": "text/html,application/xhtml+xml,application/xml;q=0.9,*/*;q=0.8", "User-Agent": "Mozilla/5.0 (X11; Linux x86_64; rv:59.0) Gecko/20100101 Firefox/59.0"}, "tbr": 96.952, "container": "webm", "format": "278 - 256x144 (144p)", "url": "https://r4---sn-a5msen7s.googlevideo.com/videoplayback?id=o-ALIJ9sEEPf5QikT_nLBjAyt4-Tmd2IiQkPg8-AmO_ZWj&aitags=133%2C134%2C135%2C136%2C160%2C242%2C243%2C244%2C247%2C278%2C298%2C302&itag=278&source=youtube&requiressl=yes&mm=31%2C26&mn=sn-a5msen7s%2Csn-o097znlk&ms=au%2Conr&mv=m&pl=21&ei=XAvTXNSxB82FkwatuLegDQ&initcwndbps=538750&mime=video%2Fwebm&gir=yes&clen=9689093&dur=899.999&lmt=1544310037626014&mt=1557334713&fvip=2&keepalive=yes&c=WEB&txp=1301222&ip=155.94.169.201&ipbits=0&expire=1557356476&sparams=ip%2Cipbits%2Cexpire%2Cid%2Caitags%2Csource%2Crequiressl%2Cmm%2Cmn%2Cms%2Cmv%2Cpl%2Cei%2Cinitcwndbps%2Cmime%2Cgir%2Cclen%2Cdur%2Clmt&signature=CD729551553FD4115D47424673A50885C59559BE.5ACA77538FCA16DB1B8D77E6E10E8C758DCA6FB4&key=yt8&ratebypass=yes", "vcodec": "vp9", "format_note": "144p", "player_url": "/yts/jsbin/player_ias-vflmRtaf6/en_US/base.js", "downloader_options": {"http_chunk_size": 10485760}, "width": 256, "ext": "webm", "filesize": 9689093, "fps": 30, "protocol": "https", "format_id": "278", "height": 144, "quality": -1, "acodec": "none"}, {"format_note": "360p", "protocol": "https", "format": "134 - 640x360 (360p)", "tbr": 129.233, "height": 360, "downloader_options": {"http_chunk_size": 10485760}, "format_id": "134", "quality": -1, "http_headers": {"Accept-Charset": "ISO-8859-1,utf-8;q=0.7,*;q=0.7", "Accept-Language": "en-us,en;q=0.5", "Accept-Encoding": "gzip, deflate", "Accept": "text/html,application/xhtml+xml,application/xml;q=0.9,*/*;q=0.8", "User-Agent": "Mozilla/5.0 (X11; Linux x86_64; rv:59.0) Gecko/20100101 Firefox/59.0"}, "url": "https://r4---sn-a5msen7s.googlevideo.com/videoplayback?id=o-ALIJ9sEEPf5QikT_nLBjAyt4-Tmd2IiQkPg8-AmO_ZWj&aitags=133%2C134%2C135%2C136%2C160%2C242%2C243%2C244%2C247%2C278%2C298%2C302&itag=134&source=youtube&requiressl=yes&mm=31%2C26&mn=sn-a5msen7s%2Csn-o097znlk&ms=au%2Conr&mv=m&pl=21&ei=XAvTXNSxB82FkwatuLegDQ&initcwndbps=538750&mime=video%2Fmp4&gir=yes&clen=10136633&dur=899.999&lmt=1544305262577590&mt=1557334713&fvip=2&keepalive=yes&c=WEB&txp=1311222&ip=155.94.169.201&ipbits=0&expire=1557356476&sparams=ip%2Cipbits%2Cexpire%2Cid%2Caitags%2Csource%2Crequiressl%2Cmm%2Cmn%2Cms%2Cmv%2Cpl%2Cei%2Cinitcwndbps%2Cmime%2Cgir%2Cclen%2Cdur%2Clmt&signature=E8E4140984431425ECFD271681A31032B4A86D25.C4B72417BA9829E11D090AF966766428F09D3372&key=yt8&ratebypass=yes", "vcodec": "avc1.4d401e", "player_url": "/yts/jsbin/player_ias-vflmRtaf6/en_US/base.js", "width": 640, "ext": "mp4", "filesize": 10136633, "fps": 30, "acodec": "none"}, {"format_note": "240p", "protocol": "https", "format": "242 - 426x240 (240p)", "tbr": 130.255, "height": 240, "downloader_options": {"http_chunk_size": 10485760}, "format_id": "242", "quality": -1, "http_headers": {"Accept-Charset": "ISO-8859-1,utf-8;q=0.7,*;q=0.7", "Accept-Language": "en-us,en;q=0.5", "Accept-Encoding": "gzip, deflate", "Accept": "text/html,application/xhtml+xml,application/xml;q=0.9,*/*;q=0.8", "User-Agent": "Mozilla/5.0 (X11; Linux x86_64; rv:59.0) Gecko/20100101 Firefox/59.0"}, "url": "https://r4---sn-a5msen7s.googlevideo.com/videoplayback?id=o-ALIJ9sEEPf5QikT_nLBjAyt4-Tmd2IiQkPg8-AmO_ZWj&aitags=133%2C134%2C135%2C136%2C160%2C242%2C243%2C244%2C247%2C278%2C298%2C302&itag=242&source=youtube&requiressl=yes&mm=31%2C26&mn=sn-a5msen7s%2Csn-o097znlk&ms=au%2Conr&mv=m&pl=21&ei=XAvTXNSxB82FkwatuLegDQ&initcwndbps=538750&mime=video%2Fwebm&gir=yes&clen=10695402&dur=899.999&lmt=1544310037626206&mt=1557334713&fvip=2&keepalive=yes&c=WEB&txp=1301222&ip=155.94.169.201&ipbits=0&expire=1557356476&sparams=ip%2Cipbits%2Cexpire%2Cid%2Caitags%2Csource%2Crequiressl%2Cmm%2Cmn%2Cms%2Cmv%2Cpl%2Cei%2Cinitcwndbps%2Cmime%2Cgir%2Cclen%2Cdur%2Clmt&signature=11CAA2F6A7ABDC9A873A7DDE91C4470A6205DB1C.E2B9B8927A0A4185AC8D3C345944C581ADA9C28E&key=yt8&ratebypass=yes", "vcodec": "vp9", "player_url": "/yts/jsbin/player_ias-vflmRtaf6/en_US/base.js", "width": 426, "ext": "webm", "filesize": 10695402, "fps": 30, "acodec": "none"}, {"format_note": "360p", "protocol": "https", "format": "243 - 640x360 (360p)", "tbr": 285.112, "height": 360, "downloader_options": {"http_chunk_size": 10485760}, "format_id": "243", "quality": -1, "http_headers": {"Accept-Charset": "ISO-8859-1,utf-8;q=0.7,*;q=0.7", "Accept-Language": "en-us,en;q=0.5", "Accept-Encoding": "gzip, deflate", "Accept": "text/html,application/xhtml+xml,application/xml;q=0.9,*/*;q=0.8", "User-Agent": "Mozilla/5.0 (X11; Linux x86_64; rv:59.0) Gecko/20100101 Firefox/59.0"}, "url": "https://r4---sn-a5msen7s.googlevideo.com/videoplayback?id=o-ALIJ9sEEPf5QikT_nLBjAyt4-Tmd2IiQkPg8-AmO_ZWj&aitags=133%2C134%2C135%2C136%2C160%2C242%2C243%2C244%2C247%2C278%2C298%2C302&itag=243&source=youtube&requiressl=yes&mm=31%2C26&mn=sn-a5msen7s%2Csn-o097znlk&ms=au%2Conr&mv=m&pl=21&ei=XAvTXNSxB82FkwatuLegDQ&initcwndbps=538750&mime=video%2Fwebm&gir=yes&clen=25778848&dur=899.999&lmt=1544310037631021&mt=1557334713&fvip=2&keepalive=yes&c=WEB&txp=1301222&ip=155.94.169.201&ipbits=0&expire=1557356476&sparams=ip%2Cipbits%2Cexpire%2Cid%2Caitags%2Csource%2Crequiressl%2Cmm%2Cmn%2Cms%2Cmv%2Cpl%2Cei%2Cinitcwndbps%2Cmime%2Cgir%2Cclen%2Cdur%2Clmt&signature=9B7EBC7C77E10BAE6C98CC4030F08CC25EE702F2.A34E31AFA7628A3342CE934E3373C4318A9822B8&key=yt8&ratebypass=yes", "vcodec": "vp9", "player_url": "/yts/jsbin/player_ias-vflmRtaf6/en_US/base.js", "width": 640, "ext": "webm", "filesize": 25778848, "fps": 30, "acodec": "none"}, {"format_note": "480p", "protocol": "https", "format": "135 - 854x480 (480p)", "tbr": 301.578, "height": 480, "downloader_options": {"http_chunk_size": 10485760}, "format_id": "135", "quality": -1, "http_headers": {"Accept-Charset": "ISO-8859-1,utf-8;q=0.7,*;q=0.7", "Accept-Language": "en-us,en;q=0.5", "Accept-Encoding": "gzip, deflate", "Accept": "text/html,application/xhtml+xml,application/xml;q=0.9,*/*;q=0.8", "User-Agent": "Mozilla/5.0 (X11; Linux x86_64; rv:59.0) Gecko/20100101 Firefox/59.0"}, "url": "https://r4---sn-a5msen7s.googlevideo.com/videoplayback?id=o-ALIJ9sEEPf5QikT_nLBjAyt4-Tmd2IiQkPg8-AmO_ZWj&aitags=133%2C134%2C135%2C136%2C160%2C242%2C243%2C244%2C247%2C278%2C298%2C302&itag=135&source=youtube&requiressl=yes&mm=31%2C26&mn=sn-a5msen7s%2Csn-o097znlk&ms=au%2Conr&mv=m&pl=21&ei=XAvTXNSxB82FkwatuLegDQ&initcwndbps=538750&mime=video%2Fmp4&gir=yes&clen=25500289&dur=899.999&lmt=1544305262781972&mt=1557334713&fvip=2&keepalive=yes&c=WEB&txp=1311222&ip=155.94.169.201&ipbits=0&expire=1557356476&sparams=ip%2Cipbits%2Cexpire%2Cid%2Caitags%2Csource%2Crequiressl%2Cmm%2Cmn%2Cms%2Cmv%2Cpl%2Cei%2Cinitcwndbps%2Cmime%2Cgir%2Cclen%2Cdur%2Clmt&signature=01F8E69095185816AE2F14FF2714EC0DC27B9FC4.E4CFA9FF7D7DF7E53DA9EA0B2D44DCCB58458DBC&key=yt8&ratebypass=yes", "vcodec": "avc1.4d401f", "player_url": "/yts/jsbin/player_ias-vflmRtaf6/en_US/base.js", "width": 854, "ext": "mp4", "filesize": 25500289, "fps": 30, "acodec": "none"}, {"format_note": "480p", "protocol": "https", "format": "244 - 854x480 (480p)", "tbr": 571.123, "height": 480, "downloader_options": {"http_chunk_size": 10485760}, "format_id": "244", "quality": -1, "http_headers": {"Accept-Charset": "ISO-8859-1,utf-8;q=0.7,*;q=0.7", "Accept-Language": "en-us,en;q=0.5", "Accept-Encoding": "gzip, deflate", "Accept": "text/html,application/xhtml+xml,application/xml;q=0.9,*/*;q=0.8", "User-Agent": "Mozilla/5.0 (X11; Linux x86_64; rv:59.0) Gecko/20100101 Firefox/59.0"}, "url": "https://r4---sn-a5msen7s.googlevideo.com/videoplayback?id=o-ALIJ9sEEPf5QikT_nLBjAyt4-Tmd2IiQkPg8-AmO_ZWj&aitags=133%2C134%2C135%2C136%2C160%2C242%2C243%2C244%2C247%2C278%2C298%2C302&itag=244&source=youtube&requiressl=yes&mm=31%2C26&mn=sn-a5msen7s%2Csn-o097znlk&ms=au%2Conr&mv=m&pl=21&ei=XAvTXNSxB82FkwatuLegDQ&initcwndbps=538750&mime=video%2Fwebm&gir=yes&clen=54030682&dur=899.999&lmt=1544310037624631&mt=1557334713&fvip=2&keepalive=yes&c=WEB&txp=1301222&ip=155.94.169.201&ipbits=0&expire=1557356476&sparams=ip%2Cipbits%2Cexpire%2Cid%2Caitags%2Csource%2Crequiressl%2Cmm%2Cmn%2Cms%2Cmv%2Cpl%2Cei%2Cinitcwndbps%2Cmime%2Cgir%2Cclen%2Cdur%2Clmt&signature=90E8976720673EF37B08E6E48B9D4657562D1DCD.41ABB7560F518F132243A42494C5DAA375D98C8D&key=yt8&ratebypass=yes", "vcodec": "vp9", "player_url": "/yts/jsbin/player_ias-vflmRtaf6/en_US/base.js", "width": 854, "ext": "webm", "filesize": 54030682, "fps": 30, "acodec": "none"}, {"format_note": "720p", "protocol": "https", "format": "136 - 1280x720 (720p)", "tbr": 822.791, "height": 720, "downloader_options": {"http_chunk_size": 10485760}, "format_id": "136", "quality": -1, "http_headers": {"Accept-Charset": "ISO-8859-1,utf-8;q=0.7,*;q=0.7", "Accept-Language": "en-us,en;q=0.5", "Accept-Encoding": "gzip, deflate", "Accept": "text/html,application/xhtml+xml,application/xml;q=0.9,*/*;q=0.8", "User-Agent": "Mozilla/5.0 (X11; Linux x86_64; rv:59.0) Gecko/20100101 Firefox/59.0"}, "url": "https://r4---sn-a5msen7s.googlevideo.com/videoplayback?id=o-ALIJ9sEEPf5QikT_nLBjAyt4-Tmd2IiQkPg8-AmO_ZWj&aitags=133%2C134%2C135%2C136%2C160%2C242%2C243%2C244%2C247%2C278%2C298%2C302&itag=136&source=youtube&requiressl=yes&mm=31%2C26&mn=sn-a5msen7s%2Csn-o097znlk&ms=au%2Conr&mv=m&pl=21&ei=XAvTXNSxB82FkwatuLegDQ&initcwndbps=538750&mime=video%2Fmp4&gir=yes&clen=77010267&dur=899.999&lmt=1544305262978298&mt=1557334713&fvip=2&keepalive=yes&c=WEB&txp=1311222&ip=155.94.169.201&ipbits=0&expire=1557356476&sparams=ip%2Cipbits%2Cexpire%2Cid%2Caitags%2Csource%2Crequiressl%2Cmm%2Cmn%2Cms%2Cmv%2Cpl%2Cei%2Cinitcwndbps%2Cmime%2Cgir%2Cclen%2Cdur%2Clmt&signature=ACAE2AD892D553B284F573BF257094E91C8A1EDF.A1957A529E4EF80E5B042B0BD356B8EE100321BC&key=yt8&ratebypass=yes", "vcodec": "avc1.4d401f", "player_url": "/yts/jsbin/player_ias-vflmRtaf6/en_US/base.js", "width": 1280, "ext": "mp4", "filesize": 77010267, "fps": 30, "acodec": "none"}, {"format_note": "720p", "protocol": "https", "format": "247 - 1280x720 (720p)", "tbr": 1432.812, "height": 720, "downloader_options": {"http_chunk_size": 10485760}, "format_id": "247", "quality": -1, "http_headers": {"Accept-Charset": "ISO-8859-1,utf-8;q=0.7,*;q=0.7", "Accept-Language": "en-us,en;q=0.5", "Accept-Encoding": "gzip, deflate", "Accept": "text/html,application/xhtml+xml,application/xml;q=0.9,*/*;q=0.8", "User-Agent": "Mozilla/5.0 (X11; Linux x86_64; rv:59.0) Gecko/20100101 Firefox/59.0"}, "url": "https://r4---sn-a5msen7s.googlevideo.com/videoplayback?id=o-ALIJ9sEEPf5QikT_nLBjAyt4-Tmd2IiQkPg8-AmO_ZWj&aitags=133%2C134%2C135%2C136%2C160%2C242%2C243%2C244%2C247%2C278%2C298%2C302&itag=247&source=youtube&requiressl=yes&mm=31%2C26&mn=sn-a5msen7s%2Csn-o097znlk&ms=au%2Conr&mv=m&pl=21&ei=XAvTXNSxB82FkwatuLegDQ&initcwndbps=538750&mime=video%2Fwebm&gir=yes&clen=146614920&dur=899.999&lmt=1544310037626147&mt=1557334713&fvip=2&keepalive=yes&c=WEB&txp=1301222&ip=155.94.169.201&ipbits=0&expire=1557356476&sparams=ip%2Cipbits%2Cexpire%2Cid%2Caitags%2Csource%2Crequiressl%2Cmm%2Cmn%2Cms%2Cmv%2Cpl%2Cei%2Cinitcwndbps%2Cmime%2Cgir%2Cclen%2Cdur%2Clmt&signature=6F22CF7A86DA390A6E6B8363E933AC54044A56C9.4B1E27F0317EF27612F33432CFD50E3B902C7138&key=yt8&ratebypass=yes", "vcodec": "vp9", "player_url": "/yts/jsbin/player_ias-vflmRtaf6/en_US/base.js", "width": 1280, "ext": "webm", "filesize": 146614920, "fps": 30, "acodec": "none"}, {"http_headers": {"Accept-Charset": "ISO-8859-1,utf-8;q=0.7,*;q=0.7", "Accept-Language": "en-us,en;q=0.5", "Accept-Encoding": "gzip, deflate", "Accept": "text/html,application/xhtml+xml,application/xml;q=0.9,*/*;q=0.8", "User-Agent": "Mozilla/5.0 (X11; Linux x86_64; rv:59.0) Gecko/20100101 Firefox/59.0"}, "tbr": 2081.123, "protocol": "https", "format": "298 - 1280x720 (720p60)", "url": "https://r4---sn-a5msen7s.googlevideo.com/videoplayback?id=o-ALIJ9sEEPf5QikT_nLBjAyt4-Tmd2IiQkPg8-AmO_ZWj&aitags=133%2C134%2C135%2C136%2C160%2C242%2C243%2C244%2C247%2C278%2C298%2C302&itag=298&source=youtube&requiressl=yes&mm=31%2C26&mn=sn-a5msen7s%2Csn-o097znlk&ms=au%2Conr&mv=m&pl=21&ei=XAvTXNSxB82FkwatuLegDQ&initcwndbps=538750&mime=video%2Fmp4&gir=yes&clen=224852653&dur=900.015&lmt=1544305124455318&mt=1557334713&fvip=2&keepalive=yes&c=WEB&txp=1311222&ip=155.94.169.201&ipbits=0&expire=1557356476&sparams=ip%2Cipbits%2Cexpire%2Cid%2Caitags%2Csource%2Crequiressl%2Cmm%2Cmn%2Cms%2Cmv%2Cpl%2Cei%2Cinitcwndbps%2Cmime%2Cgir%2Cclen%2Cdur%2Clmt&signature=31E613274BA0C445175299F772A899622F53125A.976D18F622AC29E5183405136539348023BF5BF0&key=yt8&ratebypass=yes", "vcodec": "avc1.4d4020", "format_note": "720p60", "player_url": "/yts/jsbin/player_ias-vflmRtaf6/en_US/base.js", "downloader_options": {"http_chunk_size": 10485760}, "width": 1280, "ext": "mp4", "filesize": 224852653, "fps": 60, "format_id": "298", "height": 720, "quality": -1, "acodec": "none"}, {"http_headers": {"Accept-Charset": "ISO-8859-1,utf-8;q=0.7,*;q=0.7", "Accept-Language": "en-us,en;q=0.5", "Accept-Encoding": "gzip, deflate", "Accept": "text/html,application/xhtml+xml,application/xml;q=0.9,*/*;q=0.8", "User-Agent": "Mozilla/5.0 (X11; Linux x86_64; rv:59.0) Gecko/20100101 Firefox/59.0"}, "tbr": 2476.815, "protocol": "https", "format": "302 - 1280x720 (720p60)", "url": "https://r4---sn-a5msen7s.googlevideo.com/videoplayback?id=o-ALIJ9sEEPf5QikT_nLBjAyt4-Tmd2IiQkPg8-AmO_ZWj&aitags=133%2C134%2C135%2C136%2C160%2C242%2C243%2C244%2C247%2C278%2C298%2C302&itag=302&source=youtube&requiressl=yes&mm=31%2C26&mn=sn-a5msen7s%2Csn-o097znlk&ms=au%2Conr&mv=m&pl=21&ei=XAvTXNSxB82FkwatuLegDQ&initcwndbps=538750&mime=video%2Fwebm&gir=yes&clen=268356728&dur=900.015&lmt=1544310271651521&mt=1557334713&fvip=2&keepalive=yes&c=WEB&txp=1301222&ip=155.94.169.201&ipbits=0&expire=1557356476&sparams=ip%2Cipbits%2Cexpire%2Cid%2Caitags%2Csource%2Crequiressl%2Cmm%2Cmn%2Cms%2Cmv%2Cpl%2Cei%2Cinitcwndbps%2Cmime%2Cgir%2Cclen%2Cdur%2Clmt&signature=58E4756ADC3167AABFE9A6E4A9D9D39E59292CAF.38C7CC1196C8B7650FEE9F949A85C732FCDA31E2&key=yt8&ratebypass=yes", "vcodec": "vp9", "format_note": "720p60", "player_url": "/yts/jsbin/player_ias-vflmRtaf6/en_US/base.js", "downloader_options": {"http_chunk_size": 10485760}, "width": 1280, "ext": "webm", "filesize": 268356728, "fps": 60, "format_id": "302", "height": 720, "quality": -1, "acodec": "none"}, {"http_headers": {"Accept-Charset": "ISO-8859-1,utf-8;q=0.7,*;q=0.7", "Accept-Language": "en-us,en;q=0.5", "Accept-Encoding": "gzip, deflate", "Accept": "text/html,application/xhtml+xml,application/xml;q=0.9,*/*;q=0.8", "User-Agent": "Mozilla/5.0 (X11; Linux x86_64; rv:59.0) Gecko/20100101 Firefox/59.0"}, "protocol": "https", "format": "18 - 640x360 (medium)", "url": "https://r4---sn-a5msen7s.googlevideo.com/videoplayback?id=o-ALIJ9sEEPf5QikT_nLBjAyt4-Tmd2IiQkPg8-AmO_ZWj&itag=18&source=youtube&requiressl=yes&mm=31%2C26&mn=sn-a5msen7s%2Csn-o097znlk&ms=au%2Conr&mv=m&pl=21&ei=XAvTXNSxB82FkwatuLegDQ&initcwndbps=538750&mime=video%2Fmp4&gir=yes&clen=37541059&ratebypass=yes&dur=900.075&lmt=1544306305723672&mt=1557334713&fvip=2&c=WEB&txp=1311222&ip=155.94.169.201&ipbits=0&expire=1557356476&sparams=ip%2Cipbits%2Cexpire%2Cid%2Citag%2Csource%2Crequiressl%2Cmm%2Cmn%2Cms%2Cmv%2Cpl%2Cei%2Cinitcwndbps%2Cmime%2Cgir%2Cclen%2Cratebypass%2Cdur%2Clmt&signature=A3FB15D1870B650FD8C9E453F39C6DCA3D69A010.1297B5BFC1DC93679518D2399E5F3D3A94DF14BA&key=yt8", "quality": 1, "vcodec": "avc1.42001E", "format_note": "medium", "ext": "mp4", "player_url": "/yts/jsbin/player_ias-vflmRtaf6/en_US/base.js", "width": 640, "abr": 96, "filesize": 37541059, "format_id": "18", "height": 360, "resolution": "640x360", "acodec": "mp4a.40.2"}, {"http_headers": {"Accept-Charset": "ISO-8859-1,utf-8;q=0.7,*;q=0.7", "Accept-Language": "en-us,en;q=0.5", "Accept-Encoding": "gzip, deflate", "Accept": "text/html,application/xhtml+xml,application/xml;q=0.9,*/*;q=0.8", "User-Agent": "Mozilla/5.0 (X11; Linux x86_64; rv:59.0) Gecko/20100101 Firefox/59.0"}, "protocol": "https", "format": "43 - 640x360 (medium)", "url": "https://r4---sn-a5msen7s.googlevideo.com/videoplayback?id=o-ALIJ9sEEPf5QikT_nLBjAyt4-Tmd2IiQkPg8-AmO_ZWj&itag=43&source=youtube&requiressl=yes&mm=31%2C26&mn=sn-a5msen7s%2Csn-o097znlk&ms=au%2Conr&mv=m&pl=21&ei=XAvTXNSxB82FkwatuLegDQ&initcwndbps=538750&mime=video%2Fwebm&gir=yes&clen=73049658&ratebypass=yes&dur=0.000&lmt=1544309633559126&mt=1557334713&fvip=2&c=WEB&txp=1301222&ip=155.94.169.201&ipbits=0&expire=1557356476&sparams=ip%2Cipbits%2Cexpire%2Cid%2Citag%2Csource%2Crequiressl%2Cmm%2Cmn%2Cms%2Cmv%2Cpl%2Cei%2Cinitcwndbps%2Cmime%2Cgir%2Cclen%2Cratebypass%2Cdur%2Clmt&signature=330AC7AEF0DE5AF6AFF9130A6A4B3F3611CB0337.5149A155A180623BE0C70DEF157F2088746A8199&key=yt8", "quality": 1, "vcodec": "vp8.0", "format_note": "medium", "ext": "webm", "player_url": "/yts/jsbin/player_ias-vflmRtaf6/en_US/base.js", "width": 640, "abr": 128, "filesize": 73049658, "format_id": "43", "height": 360, "resolution": "640x360", "acodec": "vorbis"}, {"http_headers": {"Accept-Charset": "ISO-8859-1,utf-8;q=0.7,*;q=0.7", "Accept-Language": "en-us,en;q=0.5", "Accept-Encoding": "gzip, deflate", "Accept": "text/html,application/xhtml+xml,application/xml;q=0.9,*/*;q=0.8", "User-Agent": "Mozilla/5.0 (X11; Linux x86_64; rv:59.0) Gecko/20100101 Firefox/59.0"}, "protocol": "https", "format": "22 - 1280x720 (hd720)", "url": "https://r4---sn-a5msen7s.googlevideo.com/videoplayback?id=o-ALIJ9sEEPf5QikT_nLBjAyt4-Tmd2IiQkPg8-AmO_ZWj&itag=22&source=youtube&requiressl=yes&mm=31%2C26&mn=sn-a5msen7s%2Csn-o097znlk&ms=au%2Conr&mv=m&pl=21&ei=XAvTXNSxB82FkwatuLegDQ&initcwndbps=538750&mime=video%2Fmp4&ratebypass=yes&dur=900.075&lmt=1544307971980831&mt=1557334713&fvip=2&c=WEB&txp=1311222&ip=155.94.169.201&ipbits=0&expire=1557356476&sparams=ip%2Cipbits%2Cexpire%2Cid%2Citag%2Csource%2Crequiressl%2Cmm%2Cmn%2Cms%2Cmv%2Cpl%2Cei%2Cinitcwndbps%2Cmime%2Cratebypass%2Cdur%2Clmt&signature=B260F46D69980E67412631C23BB5051DF806B9F2.99292A3A491BA02FE6A249AB5611865827987EC8&key=yt8", "quality": 2, "vcodec": "avc1.64001F", "format_note": "hd720", "ext": "mp4", "player_url": "/yts/jsbin/player_ias-vflmRtaf6/en_US/base.js", "width": 1280, "abr": 192, "format_id": "22", "height": 720, "resolution": "1280x720", "acodec": "mp4a.40.2"}], "playlist_uploader_id": "tanglung4", "channel_url": "http://www.youtube.com/channel/UCeBfK3zzgqDQLhBovmguOuQ", "resolution": null, "width": 256, "n_entries": 190, "age_limit": 0}